{
  "$schema": "https://biomejs.dev/schemas/1.9.4/schema.json",
  "vcs": {
    "enabled": false,
    "clientKind": "git",
    "useIgnoreFile": false
  },
  "files": {
    "ignoreUnknown": false,
    "ignore": [
      "node_modules",
      ".next",
      "src/components/ui/*.tsx",
      "./contracts"
    ]
  },
  "formatter": {
    "enabled": true,
    "formatWithErrors": false,
    "indentStyle": "space",
    "indentWidth": 2,
    "lineEnding": "lf",
    "lineWidth": 80,
    "attributePosition": "auto",
    "useEditorconfig": false
  },
  "organizeImports": {
    "enabled": true
  },
  "linter": {
    "enabled": true,
    "rules": {
      "recommended": true,
      "suspicious": {
        "noDebugger": "off"
      },
      "style": {},
      "a11y": {
        "useSemanticElements": "off",
        "useKeyWithClickEvents": "off"
      },
      "correctness": {
        "noUnusedImports": "error"
      },
      "nursery": {
        "useSortedClasses": {
          "level": "warn",
          "fix": "safe",
          "options": {
            "attributes": ["className"],
            "functions": ["clsx", "cva", "cn"]
          }
        }
      }
    }
  },
  "javascript": {
    "formatter": {
      "enabled": true,
      "quoteStyle": "single",
      "jsxQuoteStyle": "single",
      "quoteProperties": "asNeeded",
      "trailingCommas": "all",
      "semicolons": "asNeeded",
      "arrowParentheses": "always",
      "indentStyle": "space",
      "indentWidth": 2,
      "lineEnding": "lf",
      "lineWidth": 80,
      "bracketSameLine": false,
      "bracketSpacing": true,
      "attributePosition": "multiline"
    }
  },
  "json": {
    "parser": {
      "allowComments": true
    },
    "formatter": {
      "enabled": true,
      "indentStyle": "space",
      "indentWidth": 2,
      "lineEnding": "lf",
      "lineWidth": 80
    }
  },
  "css": {
    "formatter": {
      "enabled": true,
      "indentStyle": "space",
      "indentWidth": 2,
      "quoteStyle": "single"
    },
    "linter": {
      "enabled": true
    }
  }
}
